[
    {
        "summary": "Auslegung technischer Baugruppen",
        "Dozent": "Austerhoff",
        "Studiengruppe": "24BTS-MAS-3, 24BTS-MEC-3",
        "globalID": "7P32XX"
    },
    {
        "summary": "Thermodynamik",
        "Dozent": "Koke",
        "Studiengruppe": "24BTS-CPV-3, 24BTS-MAS-3",
        "globalID": "8G9Z83"
    },
    {
        "summary": "Statistik",
        "Dozent": "Grunwald",
        "Studiengruppe": "24BTS-CPV-3, 24BTS-MAS-3",
        "globalID": "K6LEUN"
    },
    {
        "summary": "Mechanik: Dynamik",
        "Dozent": "Voicu",
        "Studiengruppe": "24BTS-EAT-3, 24BTS-MAS-3, 24BTS-MEC-3",
        "globalID": "OHC8KD"
    },
    {
        "summary": "Technische Physik - Physikalische Modelle",
        "Dozent": "Voicu",
        "Studiengruppe": "24BTS-MAS-3",
        "globalID": "BTX4YX"
    },
    {
        "summary": "Rechnergestütztes Konstruieren",
        "Dozent": "Leonhardt",
        "Studiengruppe": "24BTS-MAS-3",
        "globalID": "M433D7"
    },
    {
        "summary": "Infos zum Studium",
        "Dozent": "Arens-Fischer, Schlautmann-Kemner, Schultheis",
        "Studiengruppe": "24BTS-CPV-3, 24BTS-EAT-3, 24BTS-MAS-3, 24BTS-MEC-3, 24BTS-TIN-3, 24DNB1-3, 24DNB2-3, 24DNB3-3, 24DNB3-STE-3, 24DNB4-3, 24DNE1-3, 24DNE2-3, 24DNI1-3, 24DNI2-3, 24DNI2-STE-3",
        "globalID": "2V6XJS"
    },
    {
        "summary": "Metallbau (Vorbereitung Kammerprüfung)",
        "Dozent": "Scholz",
        "Studiengruppe": "24BTS-CPV-3, 24BTS-EAT-3, 24BTS-MAS-3, 24BTS-MEC-3, 24BTS-TIN-3, 24DNE1-3, 24DNE2-3",
        "globalID": "9F1HFQ"
    },
    {
        "summary": "Elektrotechnik (Vorbereitung Kammerprüfung)",
        "Dozent": "Gerdes",
        "Studiengruppe": "24BTS-CPV-3, 24BTS-EAT-3, 24BTS-MAS-3, 24BTS-MEC-3, 24BTS-TIN-3, 24DNE1-3, 24DNE2-3",
        "globalID": "FWPZCU"
    },
    {
        "summary": "Englisch",
        "Dozent": "Fitzgerald, van Heugten",
        "Studiengruppe": "24BTS-MAS-3",
        "globalID": "WHM2Y5"
    },
    {
        "summary": "Semestergespräch",
        "Dozent": "Kerperien",
        "Studiengruppe": "24BTS-CPV-3, 24BTS-EAT-3, 24BTS-MAS-3, 24BTS-MEC-3, 24BTS-TIN-3",
        "globalID": "MQV7KD"
    },
    {
        "summary": "Grundlagen Data Science",
        "Dozent": "Guericke",
        "Studiengruppe": "24BTS-CPV-3",
        "globalID": "RBBQ4C"
    },
    {
        "summary": "Technische Physik - Physikalische Modelle",
        "Dozent": "Voicu",
        "Studiengruppe": "24BTS-CPV-3, 24BTS-EAT-3, 24BTS-MEC-3, 24BTS-TIN-3",
        "globalID": "BV8YUF"
    },
    {
        "summary": "Rechnergestütztes Konstruieren",
        "Dozent": "Leonhardt",
        "Studiengruppe": "24BTS-CPV-3, 24BTS-EAT-3, 24BTS-MEC-3, 24BTS-TIN-3",
        "globalID": "46OPBW"
    },
    {
        "summary": "Englisch",
        "Dozent": "Fitzgerald, van Heugten",
        "Studiengruppe": "24BTS-CPV-3, 24BTS-EAT-3, 24BTS-MEC-3, 24BTS-TIN-3",
        "globalID": "V4LNLK"
    },
    {
        "summary": "Physikalische Chemie",
        "Dozent": "Jordan",
        "Studiengruppe": "24BTS-CPV-3",
        "globalID": "4QW4KV"
    },
    {
        "summary": "Technische Elektrodynamik",
        "Dozent": "Kling",
        "Studiengruppe": "24BTS-EAT-3, 24BTS-MEC-3",
        "globalID": "CLT1RH"
    },
    {
        "summary": "Elektrische und elektronische Bauelemente",
        "Dozent": "Voges",
        "Studiengruppe": "24BTS-EAT-3, 24BTS-MEC-3, 24BTS-TIN-3",
        "globalID": "8B63IT"
    },
    {
        "summary": "Elektrische Maschinen",
        "Dozent": "Terörde",
        "Studiengruppe": "24BTS-EAT-3, 24BTS-MEC-3, 24BTS-TIN-3",
        "globalID": "VQTEEK"
    },
    {
        "summary": "Datenbanken",
        "Dozent": "Siepermann",
        "Studiengruppe": "24BTS-TIN-3, 24DNI1-3, 24DNI2-3, 24DNI2-STE-3",
        "globalID": "D1MNGX"
    },
    {
        "summary": "Marketingpolitiken",
        "Dozent": "Diederichs",
        "Studiengruppe": "24DNI1-3",
        "globalID": "1PV715"
    },
    {
        "summary": "Statistik",
        "Dozent": "Ornau",
        "Studiengruppe": "24DNI1-3, 24DNI2-3, 24DNI2-STE-3",
        "globalID": "O3W7GO"
    },
    {
        "summary": "Informatik (Vorbereitung Kammerprüfung)",
        "Dozent": "Zilinski",
        "Studiengruppe": "24DNI1-3, 24DNI2-3, 24DNI2-STE-3",
        "globalID": "SXZXNH"
    },
    {
        "summary": "Nachhaltiges Prozessmanagement und angewandte Fallstudien",
        "Dozent": "Barenkamp",
        "Studiengruppe": "24DNI1-3, 24DNI2-3, 24DNI2-STE-3",
        "globalID": "C0VF2N"
    },
    {
        "summary": "Grundlagen Data Science",
        "Dozent": "Guericke",
        "Studiengruppe": "24DNI1-3, 24DNI2-3, 24DNI2-STE-3",
        "globalID": "942AJN"
    },
    {
        "summary": "Algorythmen und Datenstrukturen",
        "Dozent": "Streekmann",
        "Studiengruppe": "24BTS-TIN-3, 24DNI1-3",
        "globalID": "E4OJCR"
    },
    {
        "summary": "Finanzbuchhaltung / Jahresabschluss",
        "Dozent": "Neugebauer",
        "Studiengruppe": "24DNI1-3, 24DNI2-3",
        "globalID": "XIHPKB"
    },
    {
        "summary": "Internes Rechnungswesen",
        "Dozent": "Schwellnuß",
        "Studiengruppe": "24DNI1-3",
        "globalID": "4G9FXW"
    },
    {
        "summary": "Englisch",
        "Dozent": "Friedenstab",
        "Studiengruppe": "24DNI1-3",
        "globalID": "C8CE38"
    }
]